dtar/__init__.py
dtar-0.0.1.dist-info/METADATA
dtar-0.0.1.dist-info/WHEEL
dtar-0.0.1.dist-info/top_level.txt
dtar-0.0.1.dist-info/RECORD
