Metadata-Version: 2.1
Name: dtar
Version: 0.0.1
Summary: Coming soon
Author-email: datarc <datarc.co@gmail.com>
